llmshield/__init__.py
llmshield/cloak_prompt.py
llmshield/core.py
llmshield/detection_utils.py
llmshield/entity_detector.py
llmshield/error_handling.py
llmshield/exceptions.py
llmshield/lru_cache.py
llmshield/uncloak_response.py
llmshield/uncloak_stream_response.py
llmshield/utils.py
llmshield/cache/__init__.py
llmshield/cache/entity_cache.py
llmshield/matchers/__init__.py
llmshield/matchers/functions.py
llmshield/matchers/lists.py
llmshield/matchers/regex.py
llmshield/matchers/dicts/__init__.py
llmshield/matchers/dicts/cities.txt
llmshield/matchers/dicts/countries.txt
llmshield/matchers/dicts/organisations.txt
llmshield/matchers/dicts/corpus/__init__.py
llmshield/matchers/dicts/corpus/english.txt
llmshield/providers/__init__.py
llmshield/providers/anthropic_provider.py
llmshield/providers/base.py
llmshield/providers/default_provider.py
llmshield/providers/openai_provider.py
llmshield/providers/provider_factory.py
llmshield-1.0.0.dist-info/licenses/LICENSE.txt
llmshield-1.0.0.dist-info/METADATA
llmshield-1.0.0.dist-info/WHEEL
llmshield-1.0.0.dist-info/top_level.txt
llmshield-1.0.0.dist-info/RECORD
