Metadata-Version: 2.4
Name: llmshield
Version: 1.0.0
Summary: Shields your confidential data from third party LLM providers.
Author-email: Aditya Dedhia <aditya@brainpolo.com>, Sebastian Andres El Khoury Seoane <sebasandres0694@gmail.com>
Project-URL: Homepage, https://github.com/brainpolo/llmshield
Project-URL: Issues, https://github.com/brainpolo/llmshield/issues
Keywords: llm,ai,security,privacy
Classifier: Development Status :: 3 - Alpha
Classifier: Intended Audience :: Developers
Classifier: Operating System :: OS Independent
Classifier: Programming Language :: Python :: 3
Requires-Python: >=3.12
License-File: LICENSE.txt
Provides-Extra: dev
Requires-Dist: coverage>=7.8.0; extra == "dev"
Requires-Dist: build>=1.2.2; extra == "dev"
Requires-Dist: packaging>=24.2; extra == "dev"
Requires-Dist: pyproject_hooks>=1.2.0; extra == "dev"
Requires-Dist: setuptools>=78.1.1; extra == "dev"
Requires-Dist: sphinx>=8.2.3; extra == "dev"
Requires-Dist: myst-parser>=4.0.1; extra == "dev"
Requires-Dist: sphinx_rtd_theme; extra == "dev"
Requires-Dist: pre-commit>=4.2.0; extra == "dev"
Requires-Dist: ruff>=0.11.13; extra == "dev"
Requires-Dist: parameterized>=0.9.0; extra == "dev"
Requires-Dist: openai>=1.83.0; extra == "dev"
Requires-Dist: twine>=6.1.0; extra == "dev"
Dynamic: license-file
